assetkit/__init__.py
assetkit/asset_manager.py
assetkit/cli.py
assetkit/discovery.py
assetkit/scaffold.py
assetkit/cli/__init__.py
assetkit/cli/new.py
assetkit/cli/scaffold.py
assetkit/internal/cli/bundle_docker_image.py
assetkit/internal/cli/load_docker_image.py
assetkit/internal/generators/__init__.py
assetkit/internal/generators/generate_asset_map.py
assetkit/templates/asset_package/your_package_name/__init__.py
assetkit/templates/scaffolds/mlkit/cli.py
assetkit/templates/scaffolds/mlkit/core/__init__.py
assetkit/templates/scaffolds/mlkit/core/data_loader.py
assetkit/templates/scaffolds/mlkit/core/model.py
assetkit/templates/scaffolds/mlkit/core/trainer.py
assetkit-0.1.16.dist-info/licenses/LICENSE
assetkit-0.1.16.dist-info/METADATA
assetkit-0.1.16.dist-info/WHEEL
assetkit-0.1.16.dist-info/entry_points.txt
assetkit-0.1.16.dist-info/top_level.txt
assetkit-0.1.16.dist-info/RECORD
