Metadata-Version: 2.4
Name: assetkit
Version: 0.1.16
Summary: A Python toolkit for managing runtime asset packages
Author-email: docdann <docdann@proton.me>
License: MIT
Requires-Python: >=3.8
License-File: LICENSE
Dynamic: license-file
